Workbook

Sheet START HERE
B2: The Uneven Paycheck Kit
B3: Know what you can spend this week, even when every paycheck is different. v1.0
B5: Start here (takes about 10 minutes, once)
B6: 1 | C6: Baseline tab: type your take-home pay for your last 8 to 12 weeks. You get your SAFE WEEKLY NUMBER, the average of your 3 lowest weeks. That's what you plan around, not your best week.
B7: 2 | C7: Bills Calendar tab: list every bill you pay each month (rent, phone, insurance...) with its amount. The sheet works out how much to set aside from every weekly paycheck so bills are always covered.
B8: 3 | C8: Baseline tab, 'Your settings': choose a tax jar % if you want one (leave 0 if taxes are already taken out of your pay) and type how much you already have saved as a cushion.
B9: 4 | C9: Every payday: open This Week, type what you earned, and follow the colour. It tells you the 4 numbers: bills set-aside, tax jar, safe to spend, and how much goes to (or comes from) your cushion.
B10: 5 | C10: Then log that week in Year View so your cushion balance stays up to date. Rent coming up? Use the Rent Week Plan tab.
B13: What the colours mean
C14: GREEN: you're fine. Bills are covered and something goes to your cushion.
C15: YELLOW: slow week. Your cushion covers the gap, that's exactly what it's for.
C16: RED: your cushion can't cover this week. Spend only what the sheet shows and skip extras.
B18: Good to know
C19: • White cells are yours to type in. Coloured cells calculate by themselves, please don't type over them.
C20: • The example numbers are there so you can see how it works. Replace them with yours.
C21: • Google Sheets: File > Make a copy (or open the file and choose 'Save as Google Sheets'). Works on phone and laptop.
C22: • This is a budgeting tool, not tax, debt or investing advice. For your tax %, ask a tax professional what fits you.
C23: • Made by Nora, an AI creator. Template built and tested by a real human.

Sheet Baseline
B2: Baseline
B3: Your safe weekly number: the one you can count on.
B5: Week | C5: Take-home pay ($)
B6: Week 1 | C6: 620 | D6: Example numbers. Replace them with your last 8-12 weeks (rough is fine).
B7: Week 2 | C7: 380
B8: Week 3 | C8: 540
B9: Week 4 | C9: 290
B10: Week 5 | C10: 710
B11: Week 6 | C11: 450
B12: Week 7 | C12: 330
B13: Week 8 | C13: 600
B14: Week 9
B15: Week 10
B16: Week 11
B17: Week 12
B20: Your average week | C20: =IF(COUNT(C6:C17)<3,"",AVERAGE(C6:C17)) | D20: What most budgets use. It hides your slow weeks.
B21: SAFE WEEKLY NUMBER | C21: =IF(COUNT(C6:C17)<3,"Type at least 3 weeks",(SMALL(C6:C17,1)+SMALL(C6:C17,2)+SMALL(C6:C17,3))/3) | D21: Average of your 3 lowest weeks. Everything is planned around this.
B22: Weekly spending allowance | C22: =IF(ISNUMBER(C21),MAX(0,C21-Bills!$C$28-C21*C26),"") | D22: Safe number minus bills set-aside and tax jar. Groceries, gas, fun: this is your steady weekly amount.
B23: Check | C23: =IF(NOT(ISNUMBER(C21)),"",IF(Bills!$C$28+C21*C26>C21,"Bills are higher than your safe number. Look at Rent Week Plan and trim a bill.","Your bills fit inside your safe number."))
B25: Your settings
B26: Tax jar % (0 if taxes come out of your pay) | C26: 0 | D26: Type 0.25 or 25% for 25%. Not tax advice: ask a tax professional what fits you.
B27: Cushion you already have saved | C27: 200 | D27: Money set aside for slow weeks. Example: $200.

Sheet Bills
B2: Bills Calendar
B3: Every bill, its amount and its due day. The sheet spreads them across your paydays.
B5: Bill | C5: Amount per month ($) | D5: Due day (1-31) | E5: Notes
B6: Rent | C6: 750 | D6: 1 | E6: Example bills. Replace with yours. Groceries and gas are spending, not bills: leave them out.
B7: Phone | C7: 45 | D7: 12
B8: Internet | C8: 50 | D8: 5
B9: Electric | C9: 70 | D9: 20
B10: Car insurance | C10: 95 | D10: 18
B11: Streaming | C11: 20 | D11: 27
B27: Total bills per month | C27: =SUM(C6:C25)
B28: Set aside every weekly payday | C28: =C27*12/52 | E28: Monthly bills x 12 months / 52 weeks. Move this to your bills account every payday and bills are always covered.
B29: Bills due in the next 7 days | C29: =SUMPRODUCT((D6:D25<>"")*(MOD(D6:D25-DAY(TODAY()),31)<7)*C6:C25) | E29: Counts bills whose due day falls within the next week (approximate around month ends).

Sheet This Week
B2: This Week
B3: Every payday: type one number, follow the colour.
B5: What I earned this week ($) | C5: 412 | D5: Example: $412. Type your take-home pay for this week.
B7: Your 4 numbers | C7: Amount | D7: What to do
B8: 1. Bills set-aside | C8: =IF(C5="","",Bills!$C$28) | D8: Move this to your bills account (or envelope) first.
B9: 2. Tax jar | C9: =IF(C5="","",C5*Baseline!$C$26) | D9: Set this aside for taxes. 0 if taxes come out of your pay.
B10: 3. Safe to spend | C10: =IF(C5="","",IF(C11>=0,Baseline!$C$22,MAX(0,MIN(Baseline!$C$22,Baseline!$C$22+C11+C13)))) | D10: Groceries, gas, fun. Spend this and no more until next payday.
B11: 4. Cushion: add (+) or take (-) | C11: =IF(C5="","",C5-C8-C9-Baseline!$C$22) | D11: Positive: add it to your cushion. Negative: take it from your cushion.
B13: Cushion before this payday | C13: =Baseline!$C$27+SUM('Year View'!H6:H57) | D13: Comes from Year View. Log each week there after you've moved the money.
B14: Cushion after this payday | C14: =IF(C5="","",C13+C11)
B16: =IF(C5="","Type what you earned this week in the box above.",IF(C11>=0,"GREEN: You're fine. Bills are covered. Add "&TEXT(C11,"$#,##0.00")&" to your cushion.",IF(C13+C11>=0,"YELLOW: Slow week. Take "&TEXT(-C11,"$#,##0.00")&" from your cushion. That's what it's for.","RED: Your cushion can't cover this week. Pay bills first and spend only "&TEXT(C10,"$#,##0.00")&".")))
B18: How it works: your safe weekly number covers bills, tax jar and a steady spending allowance. Good weeks fill the cushion, slow weeks take from it, so your spending stays the same every week.

Sheet Year View
B2: Year View
B3: Log every week here after payday. Your cushion balance updates by itself.
B5: Week | C5: Week starting | D5: Take-home pay | E5: Tax jar | F5: Bills set-aside | G5: Safe to spend | H5: Cushion + / - | I5: Cushion balance
B6: 1 | D6: 620 | E6: =IF(D6="","",D6*Baseline!$C$26) | F6: =IF(D6="","",Bills!$C$28) | G6: =IF(D6="","",Baseline!$C$22) | H6: =IF(D6="","",D6-E6-F6-G6) | I6: =IF(D6="","",Baseline!$C$27+SUM(H$6:H6)) | K6: Example: 4 weeks filled in. Replace with yours.
B7: 2 | D7: 380 | E7: =IF(D7="","",D7*Baseline!$C$26) | F7: =IF(D7="","",Bills!$C$28) | G7: =IF(D7="","",Baseline!$C$22) | H7: =IF(D7="","",D7-E7-F7-G7) | I7: =IF(D7="","",Baseline!$C$27+SUM(H$6:H7))
B8: 3 | D8: 540 | E8: =IF(D8="","",D8*Baseline!$C$26) | F8: =IF(D8="","",Bills!$C$28) | G8: =IF(D8="","",Baseline!$C$22) | H8: =IF(D8="","",D8-E8-F8-G8) | I8: =IF(D8="","",Baseline!$C$27+SUM(H$6:H8))
B9: 4 | D9: 290 | E9: =IF(D9="","",D9*Baseline!$C$26) | F9: =IF(D9="","",Bills!$C$28) | G9: =IF(D9="","",Baseline!$C$22) | H9: =IF(D9="","",D9-E9-F9-G9) | I9: =IF(D9="","",Baseline!$C$27+SUM(H$6:H9))
B10: 5 | E10: =IF(D10="","",D10*Baseline!$C$26) | F10: =IF(D10="","",Bills!$C$28) | G10: =IF(D10="","",Baseline!$C$22) | H10: =IF(D10="","",D10-E10-F10-G10) | I10: =IF(D10="","",Baseline!$C$27+SUM(H$6:H10))
B11: 6 | E11: =IF(D11="","",D11*Baseline!$C$26) | F11: =IF(D11="","",Bills!$C$28) | G11: =IF(D11="","",Baseline!$C$22) | H11: =IF(D11="","",D11-E11-F11-G11) | I11: =IF(D11="","",Baseline!$C$27+SUM(H$6:H11))
B12: 7 | E12: =IF(D12="","",D12*Baseline!$C$26) | F12: =IF(D12="","",Bills!$C$28) | G12: =IF(D12="","",Baseline!$C$22) | H12: =IF(D12="","",D12-E12-F12-G12) | I12: =IF(D12="","",Baseline!$C$27+SUM(H$6:H12))
B13: 8 | E13: =IF(D13="","",D13*Baseline!$C$26) | F13: =IF(D13="","",Bills!$C$28) | G13: =IF(D13="","",Baseline!$C$22) | H13: =IF(D13="","",D13-E13-F13-G13) | I13: =IF(D13="","",Baseline!$C$27+SUM(H$6:H13))
B14: 9 | E14: =IF(D14="","",D14*Baseline!$C$26) | F14: =IF(D14="","",Bills!$C$28) | G14: =IF(D14="","",Baseline!$C$22) | H14: =IF(D14="","",D14-E14-F14-G14) | I14: =IF(D14="","",Baseline!$C$27+SUM(H$6:H14))
B15: 10 | E15: =IF(D15="","",D15*Baseline!$C$26) | F15: =IF(D15="","",Bills!$C$28) | G15: =IF(D15="","",Baseline!$C$22) | H15: =IF(D15="","",D15-E15-F15-G15) | I15: =IF(D15="","",Baseline!$C$27+SUM(H$6:H15))
B16: 11 | E16: =IF(D16="","",D16*Baseline!$C$26) | F16: =IF(D16="","",Bills!$C$28) | G16: =IF(D16="","",Baseline!$C$22) | H16: =IF(D16="","",D16-E16-F16-G16) | I16: =IF(D16="","",Baseline!$C$27+SUM(H$6:H16))
B17: 12 | E17: =IF(D17="","",D17*Baseline!$C$26) | F17: =IF(D17="","",Bills!$C$28) | G17: =IF(D17="","",Baseline!$C$22) | H17: =IF(D17="","",D17-E17-F17-G17) | I17: =IF(D17="","",Baseline!$C$27+SUM(H$6:H17))
B18: 13 | E18: =IF(D18="","",D18*Baseline!$C$26) | F18: =IF(D18="","",Bills!$C$28) | G18: =IF(D18="","",Baseline!$C$22) | H18: =IF(D18="","",D18-E18-F18-G18) | I18: =IF(D18="","",Baseline!$C$27+SUM(H$6:H18))
B19: 14 | E19: =IF(D19="","",D19*Baseline!$C$26) | F19: =IF(D19="","",Bills!$C$28) | G19: =IF(D19="","",Baseline!$C$22) | H19: =IF(D19="","",D19-E19-F19-G19) | I19: =IF(D19="","",Baseline!$C$27+SUM(H$6:H19))
B20: 15 | E20: =IF(D20="","",D20*Baseline!$C$26) | F20: =IF(D20="","",Bills!$C$28) | G20: =IF(D20="","",Baseline!$C$22) | H20: =IF(D20="","",D20-E20-F20-G20) | I20: =IF(D20="","",Baseline!$C$27+SUM(H$6:H20))
B21: 16 | E21: =IF(D21="","",D21*Baseline!$C$26) | F21: =IF(D21="","",Bills!$C$28) | G21: =IF(D21="","",Baseline!$C$22) | H21: =IF(D21="","",D21-E21-F21-G21) | I21: =IF(D21="","",Baseline!$C$27+SUM(H$6:H21))
... B57: 52 | E57: =IF(D57="","",D57*Baseline!$C$26) | F57: =IF(D57="","",Bills!$C$28) | G57: =IF(D57="","",Baseline!$C$22) | H57: =IF(D57="","",D57-E57-F57-G57) | I57: =IF(D57="","",Baseline!$C$27+SUM(H$6:H57))

Sheet Cushion
B2: Cushion Tracker
B3: Your money for slow weeks, and how many slow weeks it covers.
B5: Cushion balance now | C5: =Baseline!$C$27+SUM('Year View'!H6:H57) | D5: Starting cushion plus every week you logged.
B6: Weeks of bills it covers | C6: =IF(Bills!$C$28=0,"",C5/Bills!$C$28) | D6: If you earned nothing at all, bills would be covered this many weeks.
B7: Gap in your worst week | C7: =IF(COUNT(Baseline!$C$6:$C$17)=0,"",MAX(0,Bills!$C$28+Baseline!$C$22-MIN(Baseline!$C$6:$C$17)*(1-Baseline!$C$26))) | D7: How much your lowest week falls short of bills + spending allowance.
B8: Worst weeks it covers in a row | C8: =IF(C7="","",IF(C7=0,"Every week is covered",C5/C7)) | D8: How many of your worst weeks in a row the cushion can absorb.
B10: Cushion goal (4 weeks of bills + spending) | C10: =4*(Bills!$C$28+Baseline!$C$22) | D10: A good first goal. Raise it once you get there.
B11: Progress to goal | C11: =IF(C10=0,"",MIN(1,MAX(0,C5/C10)))

Sheet Rent Week Plan
B2: Rent Week Plan
B3: Split rent across every payday so rent week is just another week.
B5: Rent amount | C5: =Bills!C6 | D5: From the first line of Bills Calendar. Type over it if different.
B6: Paydays left before rent is due | C6: 4 | D6: Count your paydays between today and the due date.
B7: Already set aside for rent | C7: 300 | D7: Example: $300. What's already in your rent envelope.
B8: Still needed | C8: =MAX(0,C5-C7)
B9: Set aside each payday until rent | C9: =IF(C6<=0,C8,C8/C6) | D9: Move this every payday, before anything else.
B12: If rent week is tight
B13: ☐ Pay rent first, the moment you have it. Everything else waits.
B14: ☐ Look at Bills Calendar: can any bill move its due date to after rent? Many companies let you choose.
B15: ☐ Pause one subscription this month. You can turn it back on later.
B16: ☐ Use your cushion for the gap. That's what it's for, no guilt.
B17: ☐ Pick up one extra shift only if you need to, and send all of it to rent.
B18: ☐ Next month, start the rent slices one payday earlier.
